{
  "__version__": "1.3.9",
  "log": {
    "level": 4
  },
  "common": {
    "binGroupConfig": {
      "threshold": 16,
      "enable": false
    },
    "polyfills": {
      "asyncFunctions": true
    },
    "buildPath": "project://build",
    "outputName": "wechatgame",
    "mainBundleCompressionType": "merge_dep",
    "platform": "wechatgame",
    "md5Cache": false,
    "experimentalEraseModules": false
  },
  "BuildTaskManager": {
    "taskMap": {
      "1778319963035": {
        "type": "build",
        "id": "1778319963035",
        "progress": 1,
        "state": "success",
        "stage": "build",
        "message": "2026-5-10 01:59:02 build success in 4 s!",
        "detailMessage": "// ---- build task 整理部分构建选项内数据到 settings.json ----\r",
        "options": {
          "name": "yanten-games",
          "server": "",
          "engineModulesConfigKey": "defaultConfig",
          "platform": "wechatgame",
          "buildPath": "project://build",
          "debug": false,
          "buildMode": "normal",
          "mangleProperties": false,
          "md5Cache": false,
          "skipCompressTexture": false,
          "sourceMaps": false,
          "overwriteProjectSettings": {
            "macroConfig": {
              "cleanupImageCache": "on"
            },
            "includeModules": {
              "physics": "inherit-project-setting",
              "physics-2d": "inherit-project-setting",
              "gfx-webgl2": "off"
            }
          },
          "nativeCodeBundleMode": "wasm",
          "polyfills": {
            "asyncFunctions": false
          },
          "experimentalEraseModules": false,
          "startSceneAssetBundle": false,
          "bundleConfigs": [],
          "inlineEnum": true,
          "useBuiltinServer": false,
          "md5CacheOptions": {
            "excludes": [],
            "includes": [],
            "replaceOnly": [],
            "handleTemplateMd5Link": true
          },
          "mainBundleIsRemote": false,
          "mainBundleCompressionType": "merge_dep",
          "useSplashScreen": true,
          "bundleCommonChunk": false,
          "packAutoAtlas": true,
          "startScene": "85d0a394-a240-4ec1-87c5-550571651680",
          "outputName": "wechatgame",
          "taskName": "wechatgame",
          "scenes": [
            {
              "url": "db://assets/scenes/MainScene.scene",
              "uuid": "85d0a394-a240-4ec1-87c5-550571651680"
            }
          ],
          "wasmCompressionMode": false,
          "binGroupConfig": {
            "threshold": 16,
            "enable": false
          },
          "packages": {},
          "__version__": "1.3.9",
          "logDest": "project://temp/builder/log/wechatgame5-9-2026 17-46.log"
        },
        "time": "5-10-2026 01:58:57",
        "dirty": false
      }
    }
  }
}
